fast_jieba-0.4.0.dist-info/METADATA
fast_jieba-0.4.0.dist-info/WHEEL
fast_jieba/__init__.pyi
fast_jieba/__init__.py
fast_jieba/analyse/__init__.pyi
fast_jieba/analyse/__init__.py
fast_jieba/fast_jieba.cpython-39-darwin.so
fast_jieba-0.4.0.dist-info/RECORD
