Metadata-Version: 2.1
Name: fast_jieba
Version: 0.4.0
Summary: faster word segmentation tool, based on jieba_rs
Requires-Python: >=3.7
